instrbuilder/__init__.py
instrbuilder/aardvark_py.py
instrbuilder/command.py
instrbuilder/config.py
instrbuilder/ic.py
instrbuilder/instrument_opening.py
instrbuilder/instruments.py
instrbuilder/scpi.py
instrbuilder/utils.py
instrbuilder/bluesky_demo/__init__.py
instrbuilder/bluesky_demo/fg_oscilloscope_basics.py
instrbuilder/bluesky_demo/save_data.py
instrbuilder/bluesky_demo/lockin_analysis/__init__.py
instrbuilder/bluesky_demo/lockin_analysis/dynamic_reserve_ada2200_analysis.py
instrbuilder/bluesky_demo/lockin_analysis/dynamic_reserve_sr810_analysis.py
instrbuilder/bluesky_demo/lockin_analysis/freq_res_sr810_analysis.py
instrbuilder/bluesky_demo/lockin_analysis/metadata_parsing.py
instrbuilder/bluesky_demo/lockin_analysis/phase_res_ada2200_analysis.py
instrbuilder/bluesky_demo/lockin_analysis/phase_tuning_ada2200_analysis.py
instrbuilder/bluesky_demo/lockin_analysis/plot_configs.py
instrbuilder/bluesky_demo/lockin_analysis/run_all_analysis.py
instrbuilder/bluesky_demo/lockin_analysis/snr_ada2200_analysis.py
instrbuilder/bluesky_demo/lockin_analysis/snr_sr810_analysis.py
instrbuilder/bluesky_demo/lockin_tests/__init__.py
instrbuilder/bluesky_demo/lockin_tests/ada2200_filters.py
instrbuilder/bluesky_demo/lockin_tests/ada2200_spi_tests.py
instrbuilder/bluesky_demo/lockin_tests/dynamic_reserve_ada2200.py
instrbuilder/bluesky_demo/lockin_tests/dynamic_reserve_sr810.py
instrbuilder/bluesky_demo/lockin_tests/freq_res_sr810.py
instrbuilder/bluesky_demo/lockin_tests/phase_res_ada2200.py
instrbuilder/bluesky_demo/lockin_tests/snr_ada2200.py
instrbuilder/bluesky_demo/lockin_tests/snr_sr810.py
instrbuilder/bluesky_utils/__init__.py
instrbuilder/bluesky_utils/metadata.py
instrbuilder/bluesky_utils/metadata_example.py
instrbuilder/example_yaml/config.yaml
instrbuilder/examples/__init__.py
instrbuilder/examples/ad5933.py
instrbuilder/examples/ada2200.py
instrbuilder/examples/add_instruments_to_config.py
instrbuilder/examples/dmm.py
instrbuilder/examples/function_gen.py
instrbuilder-0.1.14.dist-info/AUTHORS.md
instrbuilder-0.1.14.dist-info/LICENSE
instrbuilder-0.1.14.dist-info/METADATA
instrbuilder-0.1.14.dist-info/WHEEL
instrbuilder-0.1.14.dist-info/top_level.txt
instrbuilder-0.1.14.dist-info/RECORD
