Metadata-Version: 2.1
Name: instrbuilder
Version: 0.1.14
Summary: electrical instrument control
Home-page: https://lucask07.github.io/instrbuilder/build/html/
Author: Lucas J. Koerner
Author-email: koerner.lucas@stthomas.edu
License: MIT
Platform: UNKNOWN
Classifier: Programming Language :: Python :: 3
Classifier: License :: OSI Approved :: MIT License
Classifier: Operating System :: OS Independent
License-File: LICENSE
License-File: AUTHORS.md
Requires-Dist: tabulate
Requires-Dist: scipy
Requires-Dist: pandas
Requires-Dist: setuptools
Requires-Dist: numpy
Requires-Dist: PyVISA
Requires-Dist: oyaml
Requires-Dist: sphinx-rtd-theme
Requires-Dist: databroker
Requires-Dist: colorama
Requires-Dist: matplotlib
Requires-Dist: bluesky
Requires-Dist: pyserial
Requires-Dist: wrapt
Requires-Dist: PyYAML
Requires-Dist: pytest
